{
	"name": "兴安盟",
	"features": [
		{
			"properties": {
				"lat": 45.6287,
				"lng": 121.483,
				"CNAME": "突泉县",
				"ASCRIPTION": "",
				"GB": "152224"
			},
			"geometry": {
				"points": [],
				"coordinates": [
					[
						[
							45.81698,
							121.75159
						],
						[
							45.86178,
							121.68539
						],
						[
							45.89588,
							121.65539
						],
						[
							45.89858,
							121.59789
						],
						[
							45.87308,
							121.58139
						],
						[
							45.86048,
							121.52869
						],
						[
							45.86548,
							121.49139
						],
						[
							45.88528,
							121.44939
						],
						[
							45.87948,
							121.41819
						],
						[
							45.89998,
							121.37979
						],
						[
							45.95318,
							121.34279
						],
						[
							45.94188,
							121.31919
						],
						[
							45.95588,
							121.28329
						],
						[
							46.01008,
							121.26599
						],
						[
							46.02498,
							121.24759
						],
						[
							46.02888,
							121.17809
						],
						[
							46.05928,
							121.12999
						],
						[
							46.08508,
							121.12649
						],
						[
							46.08248,
							121.07009
						],
						[
							46.05208,
							121.06939
						],
						[
							46.03268,
							121.05019
						],
						[
							45.98878,
							121.05949
						],
						[
							45.96588,
							121.01789
						],
						[
							45.94588,
							120.95369
						],
						[
							45.91038,
							120.90469
						],
						[
							45.89688,
							120.86419
						],
						[
							45.89268,
							120.79159
						],
						[
							45.84508,
							120.73329
						],
						[
							45.81828,
							120.77849
						],
						[
							45.81668,
							120.81259
						],
						[
							45.74008,
							120.91849
						],
						[
							45.74678,
							120.94639
						],
						[
							45.70848,
							121.02379
						],
						[
							45.67328,
							121.04879
						],
						[
							45.66058,
							121.10019
						],
						[
							45.60288,
							121.11239
						],
						[
							45.59438,
							121.18019
						],
						[
							45.54878,
							121.19319
						],
						[
							45.51268,
							121.24419
						],
						[
							45.51318,
							121.27789
						],
						[
							45.53038,
							121.31329
						],
						[
							45.48048,
							121.34619
						],
						[
							45.48808,
							121.37939
						],
						[
							45.44668,
							121.39089
						],
						[
							45.42188,
							121.41809
						],
						[
							45.37838,
							121.42189
						],
						[
							45.36278,
							121.47329
						],
						[
							45.28588,
							121.51389
						],
						[
							45.26688,
							121.57439
						],
						[
							45.23408,
							121.65239
						],
						[
							45.23168,
							121.68799
						],
						[
							45.19598,
							121.80409
						],
						[
							45.20658,
							121.82379
						],
						[
							45.21948,
							121.96629
						],
						[
							45.22998,
							122.00499
						],
						[
							45.26958,
							122.04779
						],
						[
							45.28388,
							122.08369
						],
						[
							45.29338,
							122.14129
						],
						[
							45.37238,
							122.14089
						],
						[
							45.40748,
							122.17389
						],
						[
							45.44388,
							122.15189
						],
						[
							45.45118,
							122.11519
						],
						[
							45.48818,
							122.01749
						],
						[
							45.50588,
							121.99659
						],
						[
							45.55088,
							121.98759
						],
						[
							45.59428,
							121.96079
						],
						[
							45.59698,
							121.99029
						],
						[
							45.62128,
							121.99749
						],
						[
							45.69088,
							121.96439
						],
						[
							45.70918,
							121.94339
						],
						[
							45.71788,
							121.86139
						],
						[
							45.70288,
							121.80639
						],
						[
							45.68528,
							121.80349
						],
						[
							45.69988,
							121.70809
						],
						[
							45.72568,
							121.66069
						],
						[
							45.75068,
							121.63849
						],
						[
							45.76838,
							121.65109
						],
						[
							45.76138,
							121.68229
						],
						[
							45.79288,
							121.74819
						],
						[
							45.81698,
							121.75159
						]
					]
				],
				"type": "Polygon"
			},
			"type": "Feature"
		},
		{
			"properties": {
				"lat": 45.2461,
				"lng": 121.014,
				"CNAME": "科尔沁右翼中旗",
				"ASCRIPTION": "",
				"GB": "152222"
			},
			"geometry": {
				"points": [],
				"coordinates": [
					[
						[
							45.84508,
							120.73329
						],
						[
							45.84808,
							120.70289
						],
						[
							45.82658,
							120.63759
						],
						[
							45.82438,
							120.58439
						],
						[
							45.86458,
							120.52109
						],
						[
							45.84928,
							120.44589
						],
						[
							45.82318,
							120.41399
						],
						[
							45.83848,
							120.39709
						],
						[
							45.87968,
							120.38599
						],
						[
							45.89918,
							120.32749
						],
						[
							45.87878,
							120.28039
						],
						[
							45.91568,
							120.21609
						],
						[
							45.94938,
							120.20719
						],
						[
							45.98328,
							120.21869
						],
						[
							46.01478,
							120.18749
						],
						[
							46.05008,
							120.20029
						],
						[
							46.06188,
							120.17889
						],
						[
							46.06728,
							120.11269
						],
						[
							46.05578,
							120.09139
						],
						[
							46.06008,
							120.04759
						],
						[
							46.09008,
							120.06309
						],
						[
							46.10248,
							120.01889
						],
						[
							46.17888,
							119.92699
						],
						[
							46.20988,
							119.91169
						],
						[
							46.20848,
							119.88269
						],
						[
							46.18308,
							119.85169
						],
						[
							46.14278,
							119.87289
						],
						[
							46.10638,
							119.84879
						],
						[
							46.00268,
							119.82749
						],
						[
							45.81878,
							119.80139
						],
						[
							45.76098,
							119.74459
						],
						[
							45.73468,
							119.69369
						],
						[
							45.70118,
							119.70219
						],
						[
							45.66768,
							119.67499
						],
						[
							45.66828,
							119.58979
						],
						[
							45.65408,
							119.55889
						],
						[
							45.62188,
							119.64909
						],
						[
							45.57728,
							119.74979
						],
						[
							45.56258,
							119.78449
						],
						[
							45.56758,
							119.83499
						],
						[
							45.54568,
							119.86549
						],
						[
							45.55648,
							119.91269
						],
						[
							45.49798,
							119.90849
						],
						[
							45.50138,
							119.93589
						],
						[
							45.48018,
							119.99309
						],
						[
							45.49748,
							120.02529
						],
						[
							45.52408,
							120.02239
						],
						[
							45.55128,
							119.98789
						],
						[
							45.57678,
							119.98859
						],
						[
							45.59318,
							120.02199
						],
						[
							45.59228,
							120.07759
						],
						[
							45.58248,
							120.13649
						],
						[
							45.59288,
							120.15949
						],
						[
							45.56858,
							120.22989
						],
						[
							45.55028,
							120.26299
						],
						[
							45.55468,
							120.31129
						],
						[
							45.51728,
							120.33969
						],
						[
							45.49748,
							120.41329
						],
						[
							45.46228,
							120.42879
						],
						[
							45.46208,
							120.48829
						],
						[
							45.41298,
							120.55239
						],
						[
							45.35598,
							120.54839
						],
						[
							45.34578,
							120.58539
						],
						[
							45.29588,
							120.65469
						],
						[
							45.25818,
							120.73749
						],
						[
							45.25128,
							120.82219
						],
						[
							45.21438,
							120.82929
						],
						[
							45.21588,
							120.87599
						],
						[
							45.18238,
							120.96209
						],
						[
							45.16778,
							120.97319
						],
						[
							45.12468,
							120.94909
						],
						[
							45.11168,
							120.97769
						],
						[
							45.07058,
							120.97149
						],
						[
							45.02698,
							120.99689
						],
						[
							44.99668,
							121.02709
						],
						[
							44.98018,
							121.06999
						],
						[
							44.95578,
							121.16359
						],
						[
							44.93208,
							121.23429
						],
						[
							44.87588,
							121.34599
						],
						[
							44.84958,
							121.37489
						],
						[
							44.84918,
							121.39549
						],
						[
							44.81608,
							121.41419
						],
						[
							44.78878,
							121.40309
						],
						[
							44.71858,
							121.52439
						],
						[
							44.66588,
							121.54269
						],
						[
							44.63828,
							121.57979
						],
						[
							44.56738,
							121.63749
						],
						[
							44.53278,
							121.69189
						],
						[
							44.47628,
							121.75409
						],
						[
							44.44468,
							121.77269
						],
						[
							44.42768,
							121.81689
						],
						[
							44.40958,
							121.82379
						],
						[
							44.40028,
							121.87709
						],
						[
							44.34168,
							121.92889
						],
						[
							44.32838,
							121.97749
						],
						[
							44.30188,
							122.01339
						],
						[
							44.25328,
							122.15809
						],
						[
							44.26168,
							122.22069
						],
						[
							44.25358,
							122.26579
						],
						[
							44.30818,
							122.28599
						],
						[
							44.40888,
							122.28879
						],
						[
							44.47578,
							122.28049
						],
						[
							44.47818,
							122.22249
						],
						[
							44.52428,
							122.21839
						],
						[
							44.55778,
							122.19029
						],
						[
							44.57538,
							122.12579
						],
						[
							44.61338,
							122.10749
						],
						[
							44.67188,
							122.09709
						],
						[
							44.70008,
							122.11149
						],
						[
							44.72618,
							122.15549
						],
						[
							44.74178,
							122.14659
						],
						[
							44.73418,
							122.09679
						],
						[
							44.77448,
							122.10899
						],
						[
							44.79738,
							122.08639
						],
						[
							44.87998,
							122.06449
						],
						[
							44.95078,
							122.08079
						],
						[
							45.00448,
							122.06859
						],
						[
							45.01938,
							122.09289
						],
						[
							45.06638,
							122.11339
						],
						[
							45.13988,
							122.10379
						],
						[
							45.18088,
							122.13729
						],
						[
							45.17858,
							122.18679
						],
						[
							45.20478,
							122.22429
						],
						[
							45.27428,
							122.23319
						],
						[
							45.29338,
							122.14129
						],
						[
							45.28388,
							122.08369
						],
						[
							45.26958,
							122.04779
						],
						[
							45.22998,
							122.00499
						],
						[
							45.21948,
							121.96629
						],
						[
							45.20658,
							121.82379
						],
						[
							45.19598,
							121.80409
						],
						[
							45.23168,
							121.68799
						],
						[
							45.23408,
							121.65239
						],
						[
							45.26688,
							121.57439
						],
						[
							45.28588,
							121.51389
						],
						[
							45.36278,
							121.47329
						],
						[
							45.37838,
							121.42189
						],
						[
							45.42188,
							121.41809
						],
						[
							45.44668,
							121.39089
						],
						[
							45.48808,
							121.37939
						],
						[
							45.48048,
							121.34619
						],
						[
							45.53038,
							121.31329
						],
						[
							45.51318,
							121.27789
						],
						[
							45.51268,
							121.24419
						],
						[
							45.54878,
							121.19319
						],
						[
							45.59438,
							121.18019
						],
						[
							45.60288,
							121.11239
						],
						[
							45.66058,
							121.10019
						],
						[
							45.67328,
							121.04879
						],
						[
							45.70848,
							121.02379
						],
						[
							45.74678,
							120.94639
						],
						[
							45.74008,
							120.91849
						],
						[
							45.81668,
							120.81259
						],
						[
							45.81828,
							120.77849
						],
						[
							45.84508,
							120.73329
						]
					]
				],
				"type": "Polygon"
			},
			"type": "Feature"
		},
		{
			"properties": {
				"lat": 46.1098,
				"lng": 122.071,
				"CNAME": "乌兰浩特市",
				"ASCRIPTION": "",
				"GB": "152201"
			},
			"geometry": {
				"points": [],
				"coordinates": [
					[
						[
							45.92848,
							122.06509
						],
						[
							45.95348,
							122.12189
						],
						[
							45.98848,
							122.13459
						],
						[
							46.01998,
							122.28849
						],
						[
							46.04638,
							122.30949
						],
						[
							46.08848,
							122.29019
						],
						[
							46.11938,
							122.25349
						],
						[
							46.14578,
							122.20679
						],
						[
							46.17378,
							122.20979
						],
						[
							46.18118,
							122.17389
						],
						[
							46.20458,
							122.15589
						],
						[
							46.20808,
							122.12159
						],
						[
							46.24338,
							122.10869
						],
						[
							46.27668,
							122.12019
						],
						[
							46.28598,
							122.04019
						],
						[
							46.26458,
							122.00559
						],
						[
							46.29398,
							121.92889
						],
						[
							46.28248,
							121.88539
						],
						[
							46.25578,
							121.89029
						],
						[
							46.22548,
							121.91479
						],
						[
							46.19318,
							121.90139
						],
						[
							46.13568,
							121.97409
						],
						[
							46.11488,
							121.97059
						],
						[
							46.08068,
							121.99839
						],
						[
							46.04488,
							121.89929
						],
						[
							46.04808,
							121.86389
						],
						[
							46.02258,
							121.83579
						],
						[
							46.00068,
							121.85829
						],
						[
							46.00328,
							121.91769
						],
						[
							45.97418,
							121.96929
						],
						[
							45.95658,
							122.03439
						],
						[
							45.92848,
							122.06509
						]
					]
				],
				"type": "Polygon"
			},
			"type": "Feature"
		},
		{
			"properties": {
				"lat": 46.3444,
				"lng": 121.259,
				"CNAME": "科尔沁右翼前旗",
				"ASCRIPTION": "",
				"GB": "152221"
			},
			"geometry": {
				"points": [],
				"coordinates": [
					[
						[
							46.92948,
							121.33609
						],
						[
							46.93538,
							121.24649
						],
						[
							46.91738,
							121.21999
						],
						[
							46.93558,
							121.15569
						],
						[
							46.95658,
							121.14379
						],
						[
							46.98868,
							121.08729
						],
						[
							47.01048,
							121.08019
						],
						[
							47.02428,
							120.98559
						],
						[
							47.00558,
							120.94789
						],
						[
							47.00008,
							120.90289
						],
						[
							46.94648,
							120.87349
						],
						[
							46.91058,
							120.82429
						],
						[
							46.90738,
							120.79379
						],
						[
							46.86328,
							120.77859
						],
						[
							46.83448,
							120.82209
						],
						[
							46.78648,
							120.83689
						],
						[
							46.75858,
							120.81559
						],
						[
							46.72378,
							120.82109
						],
						[
							46.69598,
							120.84929
						],
						[
							46.67968,
							120.78249
						],
						[
							46.68478,
							120.73489
						],
						[
							46.67088,
							120.67979
						],
						[
							46.67968,
							120.65469
						],
						[
							46.66498,
							120.56659
						],
						[
							46.68768,
							120.55259
						],
						[
							46.69988,
							120.49419
						],
						[
							46.71948,
							120.47039
						],
						[
							46.74738,
							120.40009
						],
						[
							46.74548,
							120.34529
						],
						[
							46.75828,
							120.32059
						],
						[
							46.77308,
							120.25119
						],
						[
							46.80398,
							120.20749
						],
						[
							46.80598,
							120.15159
						],
						[
							46.84198,
							120.06139
						],
						[
							46.87288,
							120.04869
						],
						[
							46.90238,
							120.01149
						],
						[
							46.91398,
							119.97749
						],
						[
							46.90238,
							119.92089
						],
						[
							46.86558,
							119.89899
						],
						[
							46.84838,
							119.91969
						],
						[
							46.79878,
							119.93149
						],
						[
							46.75198,
							119.90699
						],
						[
							46.72168,
							119.92989
						],
						[
							46.66608,
							119.90349
						],
						[
							46.65148,
							119.90399
						],
						[
							46.60658,
							119.94289
						],
						[
							46.53538,
							119.90109
						],
						[
							46.49198,
							119.94259
						],
						[
							46.42738,
							119.90319
						],
						[
							46.41798,
							119.95459
						],
						[
							46.39398,
							119.95519
						],
						[
							46.40208,
							119.89449
						],
						[
							46.37388,
							119.83099
						],
						[
							46.31768,
							119.84449
						],
						[
							46.27638,
							119.83089
						],
						[
							46.23368,
							119.82919
						],
						[
							46.20848,
							119.88269
						],
						[
							46.20988,
							119.91169
						],
						[
							46.17888,
							119.92699
						],
						[
							46.10248,
							120.01889
						],
						[
							46.09008,
							120.06309
						],
						[
							46.06008,
							120.04759
						],
						[
							46.05578,
							120.09139
						],
						[
							46.06728,
							120.11269
						],
						[
							46.06188,
							120.17889
						],
						[
							46.05008,
							120.20029
						],
						[
							46.01478,
							120.18749
						],
						[
							45.98328,
							120.21869
						],
						[
							45.94938,
							120.20719
						],
						[
							45.91568,
							120.21609
						],
						[
							45.87878,
							120.28039
						],
						[
							45.89918,
							120.32749
						],
						[
							45.87968,
							120.38599
						],
						[
							45.83848,
							120.39709
						],
						[
							45.82318,
							120.41399
						],
						[
							45.84928,
							120.44589
						],
						[
							45.86458,
							120.52109
						],
						[
							45.82438,
							120.58439
						],
						[
							45.82658,
							120.63759
						],
						[
							45.84808,
							120.70289
						],
						[
							45.84508,
							120.73329
						],
						[
							45.89268,
							120.79159
						],
						[
							45.89688,
							120.86419
						],
						[
							45.91038,
							120.90469
						],
						[
							45.94588,
							120.95369
						],
						[
							45.96588,
							121.01789
						],
						[
							45.98878,
							121.05949
						],
						[
							46.03268,
							121.05019
						],
						[
							46.05208,
							121.06939
						],
						[
							46.08248,
							121.07009
						],
						[
							46.08508,
							121.12649
						],
						[
							46.05928,
							121.12999
						],
						[
							46.02888,
							121.17809
						],
						[
							46.02498,
							121.24759
						],
						[
							46.01008,
							121.26599
						],
						[
							45.95588,
							121.28329
						],
						[
							45.94188,
							121.31919
						],
						[
							45.95318,
							121.34279
						],
						[
							45.89998,
							121.37979
						],
						[
							45.87948,
							121.41819
						],
						[
							45.88528,
							121.44939
						],
						[
							45.86548,
							121.49139
						],
						[
							45.86048,
							121.52869
						],
						[
							45.87308,
							121.58139
						],
						[
							45.89858,
							121.59789
						],
						[
							45.89588,
							121.65539
						],
						[
							45.86178,
							121.68539
						],
						[
							45.81698,
							121.75159
						],
						[
							45.87108,
							121.79759
						],
						[
							45.91628,
							121.81539
						],
						[
							46.00148,
							121.77949
						],
						[
							46.02258,
							121.83579
						],
						[
							46.04808,
							121.86389
						],
						[
							46.04488,
							121.89929
						],
						[
							46.08068,
							121.99839
						],
						[
							46.11488,
							121.97059
						],
						[
							46.13568,
							121.97409
						],
						[
							46.19318,
							121.90139
						],
						[
							46.22548,
							121.91479
						],
						[
							46.25578,
							121.89029
						],
						[
							46.28248,
							121.88539
						],
						[
							46.29398,
							121.92889
						],
						[
							46.26458,
							122.00559
						],
						[
							46.28598,
							122.04019
						],
						[
							46.27668,
							122.12019
						],
						[
							46.24338,
							122.10869
						],
						[
							46.20808,
							122.12159
						],
						[
							46.20458,
							122.15589
						],
						[
							46.18118,
							122.17389
						],
						[
							46.17378,
							122.20979
						],
						[
							46.14578,
							122.20679
						],
						[
							46.11938,
							122.25349
						],
						[
							46.08848,
							122.29019
						],
						[
							46.04638,
							122.30949
						],
						[
							46.01998,
							122.28849
						],
						[
							45.98848,
							122.13459
						],
						[
							45.95348,
							122.12189
						],
						[
							45.92848,
							122.06509
						],
						[
							45.87988,
							122.08539
						],
						[
							45.85488,
							122.19499
						],
						[
							45.79678,
							122.25829
						],
						[
							45.81098,
							122.29569
						],
						[
							45.84228,
							122.31539
						],
						[
							45.85998,
							122.36299
						],
						[
							45.91538,
							122.35599
						],
						[
							45.91478,
							122.43989
						],
						[
							45.85628,
							122.48999
						],
						[
							45.78578,
							122.49849
						],
						[
							45.78558,
							122.51709
						],
						[
							45.81948,
							122.54929
						],
						[
							45.77628,
							122.59779
						],
						[
							45.76928,
							122.63499
						],
						[
							45.72968,
							122.64429
						],
						[
							45.69898,
							122.66559
						],
						[
							45.70308,
							122.73609
						],
						[
							45.73968,
							122.75339
						],
						[
							45.76428,
							122.78649
						],
						[
							45.83298,
							122.74659
						],
						[
							45.85468,
							122.76689
						],
						[
							45.85468,
							122.79439
						],
						[
							45.91038,
							122.82259
						],
						[
							46.07128,
							122.78709
						],
						[
							46.17768,
							122.77359
						],
						[
							46.29038,
							122.75089
						],
						[
							46.41678,
							122.67719
						],
						[
							46.44328,
							122.65709
						],
						[
							46.39648,
							122.57419
						],
						[
							46.38118,
							122.51699
						],
						[
							46.39138,
							122.46899
						],
						[
							46.38948,
							122.42399
						],
						[
							46.41698,
							122.35299
						],
						[
							46.40138,
							122.25719
						],
						[
							46.41438,
							122.24789
						],
						[
							46.44058,
							122.15109
						],
						[
							46.46098,
							122.11419
						],
						[
							46.44978,
							122.08679
						],
						[
							46.44878,
							122.02289
						],
						[
							46.49578,
							121.95819
						],
						[
							46.49378,
							121.89519
						],
						[
							46.53538,
							121.86179
						],
						[
							46.57868,
							121.79199
						],
						[
							46.60708,
							121.76909
						],
						[
							46.64608,
							121.76509
						],
						[
							46.63988,
							121.71879
						],
						[
							46.66328,
							121.69029
						],
						[
							46.65988,
							121.67009
						],
						[
							46.69808,
							121.60429
						],
						[
							46.71848,
							121.55319
						],
						[
							46.74908,
							121.50299
						],
						[
							46.78048,
							121.51729
						],
						[
							46.82668,
							121.45799
						],
						[
							46.85048,
							121.44729
						],
						[
							46.89548,
							121.45859
						],
						[
							46.91028,
							121.40739
						],
						[
							46.93318,
							121.36879
						],
						[
							46.92948,
							121.33609
						]
					]
				],
				"type": "Polygon"
			},
			"type": "Feature"
		},
		{
			"properties": {
				"lat": 46.7447,
				"lng": 122.418,
				"CNAME": "扎赉特旗",
				"ASCRIPTION": "",
				"GB": "152223"
			},
			"geometry": {
				"points": [],
				"coordinates": [
					[
						[
							46.07128,
							122.78709
						],
						[
							46.09798,
							123.03939
						],
						[
							46.12148,
							123.06339
						],
						[
							46.12798,
							123.10579
						],
						[
							46.16998,
							123.09639
						],
						[
							46.17268,
							123.12139
						],
						[
							46.20848,
							123.12189
						],
						[
							46.24608,
							123.17209
						],
						[
							46.29828,
							123.13379
						],
						[
							46.34018,
							123.08829
						],
						[
							46.43398,
							123.00439
						],
						[
							46.57508,
							123.00089
						],
						[
							46.57808,
							123.04649
						],
						[
							46.61538,
							123.03929
						],
						[
							46.62008,
							123.07109
						],
						[
							46.60128,
							123.09189
						],
						[
							46.61198,
							123.17409
						],
						[
							46.58968,
							123.19919
						],
						[
							46.61498,
							123.27269
						],
						[
							46.65968,
							123.27089
						],
						[
							46.66028,
							123.31139
						],
						[
							46.67568,
							123.35959
						],
						[
							46.68488,
							123.47549
						],
						[
							46.68838,
							123.59809
						],
						[
							46.72658,
							123.62509
						],
						[
							46.81228,
							123.62089
						],
						[
							46.86238,
							123.59289
						],
						[
							46.82418,
							123.55619
						],
						[
							46.82508,
							123.49989
						],
						[
							46.85718,
							123.47799
						],
						[
							46.94288,
							123.52159
						],
						[
							46.95528,
							123.47869
						],
						[
							46.93228,
							123.42049
						],
						[
							46.98298,
							123.33679
						],
						[
							46.99518,
							123.29569
						],
						[
							46.96278,
							123.29739
						],
						[
							46.96878,
							123.35399
						],
						[
							46.93328,
							123.39769
						],
						[
							46.90418,
							123.39979
						],
						[
							46.83618,
							123.36809
						],
						[
							46.82488,
							123.33499
						],
						[
							46.86308,
							123.29109
						],
						[
							46.85928,
							123.22789
						],
						[
							46.81928,
							123.21629
						],
						[
							46.79938,
							123.19369
						],
						[
							46.74678,
							123.16109
						],
						[
							46.73318,
							123.09509
						],
						[
							46.72378,
							123.00559
						],
						[
							46.75718,
							122.99169
						],
						[
							46.78398,
							122.92459
						],
						[
							46.82508,
							122.89309
						],
						[
							46.86078,
							122.89409
						],
						[
							46.89078,
							122.87389
						],
						[
							46.91628,
							122.89349
						],
						[
							46.95838,
							122.88929
						],
						[
							46.93778,
							122.84269
						],
						[
							46.93538,
							122.79629
						],
						[
							46.97198,
							122.76859
						],
						[
							47.00078,
							122.77209
						],
						[
							47.04498,
							122.83989
						],
						[
							47.07578,
							122.78359
						],
						[
							47.09108,
							122.68029
						],
						[
							47.12178,
							122.60849
						],
						[
							47.15368,
							122.58989
						],
						[
							47.17598,
							122.54439
						],
						[
							47.25668,
							122.48649
						],
						[
							47.27718,
							122.45529
						],
						[
							47.30258,
							122.44829
						],
						[
							47.33208,
							122.41279
						],
						[
							47.34808,
							122.41179
						],
						[
							47.30588,
							122.30999
						],
						[
							47.25868,
							122.25219
						],
						[
							47.23118,
							122.19579
						],
						[
							47.21878,
							122.13579
						],
						[
							47.17818,
							122.07759
						],
						[
							47.19918,
							122.04209
						],
						[
							47.23978,
							121.91969
						],
						[
							47.24258,
							121.88069
						],
						[
							47.27758,
							121.78979
						],
						[
							47.27878,
							121.75369
						],
						[
							47.24998,
							121.67039
						],
						[
							47.20288,
							121.63419
						],
						[
							47.17668,
							121.62659
						],
						[
							47.17238,
							121.57899
						],
						[
							47.19668,
							121.54299
						],
						[
							47.18188,
							121.49009
						],
						[
							47.18648,
							121.46909
						],
						[
							47.15608,
							121.40159
						],
						[
							47.13128,
							121.36219
						],
						[
							47.11768,
							121.34159
						],
						[
							47.05738,
							121.33479
						],
						[
							47.03788,
							121.31609
						],
						[
							46.99298,
							121.30279
						],
						[
							46.95308,
							121.30679
						],
						[
							46.92948,
							121.33609
						],
						[
							46.93318,
							121.36879
						],
						[
							46.91028,
							121.40739
						],
						[
							46.89548,
							121.45859
						],
						[
							46.85048,
							121.44729
						],
						[
							46.82668,
							121.45799
						],
						[
							46.78048,
							121.51729
						],
						[
							46.74908,
							121.50299
						],
						[
							46.71848,
							121.55319
						],
						[
							46.69808,
							121.60429
						],
						[
							46.65988,
							121.67009
						],
						[
							46.66328,
							121.69029
						],
						[
							46.63988,
							121.71879
						],
						[
							46.64608,
							121.76509
						],
						[
							46.60708,
							121.76909
						],
						[
							46.57868,
							121.79199
						],
						[
							46.53538,
							121.86179
						],
						[
							46.49378,
							121.89519
						],
						[
							46.49578,
							121.95819
						],
						[
							46.44878,
							122.02289
						],
						[
							46.44978,
							122.08679
						],
						[
							46.46098,
							122.11419
						],
						[
							46.44058,
							122.15109
						],
						[
							46.41438,
							122.24789
						],
						[
							46.40138,
							122.25719
						],
						[
							46.41698,
							122.35299
						],
						[
							46.38948,
							122.42399
						],
						[
							46.39138,
							122.46899
						],
						[
							46.38118,
							122.51699
						],
						[
							46.39648,
							122.57419
						],
						[
							46.44328,
							122.65709
						],
						[
							46.41678,
							122.67719
						],
						[
							46.29038,
							122.75089
						],
						[
							46.17768,
							122.77359
						],
						[
							46.07128,
							122.78709
						]
					]
				],
				"type": "Polygon"
			},
			"type": "Feature"
		},
		{
			"properties": {
				"lat": 47.1557,
				"lng": 120.382,
				"CNAME": "阿尔山市",
				"ASCRIPTION": "",
				"GB": "152202"
			},
			"geometry": {
				"points": [],
				"coordinates": [
					[
						[
							47.55288,
							120.48709
						],
						[
							47.57218,
							120.39549
						],
						[
							47.58988,
							120.38049
						],
						[
							47.60998,
							120.31229
						],
						[
							47.63828,
							120.28119
						],
						[
							47.65358,
							120.25759
						],
						[
							47.62088,
							120.21009
						],
						[
							47.59578,
							120.10749
						],
						[
							47.56628,
							120.05959
						],
						[
							47.55088,
							120.01339
						],
						[
							47.57988,
							119.95169
						],
						[
							47.56788,
							119.90099
						],
						[
							47.54368,
							119.87899
						],
						[
							47.49388,
							119.80619
						],
						[
							47.45358,
							119.78729
						],
						[
							47.43458,
							119.76069
						],
						[
							47.40498,
							119.64469
						],
						[
							47.35938,
							119.61079
						],
						[
							47.34568,
							119.56199
						],
						[
							47.33568,
							119.47839
						],
						[
							47.29058,
							119.55139
						],
						[
							47.24668,
							119.55919
						],
						[
							47.24698,
							119.61579
						],
						[
							47.19408,
							119.70889
						],
						[
							47.16618,
							119.71719
						],
						[
							47.13028,
							119.75599
						],
						[
							47.05758,
							119.80149
						],
						[
							47.02268,
							119.78679
						],
						[
							46.98288,
							119.81809
						],
						[
							46.95538,
							119.86799
						],
						[
							46.92008,
							119.85509
						],
						[
							46.90238,
							119.92089
						],
						[
							46.91398,
							119.97749
						],
						[
							46.90238,
							120.01149
						],
						[
							46.87288,
							120.04869
						],
						[
							46.84198,
							120.06139
						],
						[
							46.80598,
							120.15159
						],
						[
							46.80398,
							120.20749
						],
						[
							46.77308,
							120.25119
						],
						[
							46.75828,
							120.32059
						],
						[
							46.74548,
							120.34529
						],
						[
							46.74738,
							120.40009
						],
						[
							46.71948,
							120.47039
						],
						[
							46.69988,
							120.49419
						],
						[
							46.68768,
							120.55259
						],
						[
							46.66498,
							120.56659
						],
						[
							46.67968,
							120.65469
						],
						[
							46.67088,
							120.67979
						],
						[
							46.68478,
							120.73489
						],
						[
							46.67968,
							120.78249
						],
						[
							46.69598,
							120.84929
						],
						[
							46.72378,
							120.82109
						],
						[
							46.75858,
							120.81559
						],
						[
							46.78648,
							120.83689
						],
						[
							46.83448,
							120.82209
						],
						[
							46.86328,
							120.77859
						],
						[
							46.90738,
							120.79379
						],
						[
							46.91058,
							120.82429
						],
						[
							46.94648,
							120.87349
						],
						[
							47.00008,
							120.90289
						],
						[
							47.00558,
							120.94789
						],
						[
							47.02428,
							120.98559
						],
						[
							47.01048,
							121.08019
						],
						[
							46.98868,
							121.08729
						],
						[
							46.95658,
							121.14379
						],
						[
							46.93558,
							121.15569
						],
						[
							46.91738,
							121.21999
						],
						[
							46.93538,
							121.24649
						],
						[
							46.92948,
							121.33609
						],
						[
							46.95308,
							121.30679
						],
						[
							46.99298,
							121.30279
						],
						[
							47.03788,
							121.31609
						],
						[
							47.05738,
							121.33479
						],
						[
							47.11768,
							121.34159
						],
						[
							47.13128,
							121.36219
						],
						[
							47.13428,
							121.32949
						],
						[
							47.10988,
							121.24149
						],
						[
							47.13308,
							121.18889
						],
						[
							47.14238,
							121.10359
						],
						[
							47.14228,
							121.04349
						],
						[
							47.09298,
							120.96489
						],
						[
							47.10598,
							120.92679
						],
						[
							47.14888,
							120.86669
						],
						[
							47.14548,
							120.81589
						],
						[
							47.16928,
							120.77189
						],
						[
							47.21678,
							120.72909
						],
						[
							47.23828,
							120.62439
						],
						[
							47.28528,
							120.61189
						],
						[
							47.30228,
							120.62239
						],
						[
							47.33528,
							120.70179
						],
						[
							47.35598,
							120.72629
						],
						[
							47.40178,
							120.71219
						],
						[
							47.43508,
							120.64109
						],
						[
							47.47038,
							120.61689
						],
						[
							47.50398,
							120.57699
						],
						[
							47.53028,
							120.59819
						],
						[
							47.55288,
							120.48709
						]
					]
				],
				"type": "Polygon"
			},
			"type": "Feature"
		}
	],
	"type": "FeatureCollection"
}